LICENSE
MANIFEST.in
README.md
setup.py
xrff2csv/__init__.py
xrff2csv/_version.py
xrff2csv/xrff2csv.py
xrff2csv.egg-info/PKG-INFO
xrff2csv.egg-info/SOURCES.txt
xrff2csv.egg-info/dependency_links.txt
xrff2csv.egg-info/entry_points.txt
xrff2csv.egg-info/requires.txt
xrff2csv.egg-info/top_level.txt
xrff2csv.egg-info/zip-safe