Metadata-Version: 1.1
Name: xrff2csv
Version: 0.2.1
Summary: A Python tool that converts XRFF files to CSV format.
Home-page: https://github.com/rhiever/xrff2csv
Author: Randal S. Olson
Author-email: rso@randalolson.com
License: License :: OSI Approved :: MIT License
Keywords: xrff,csv,converter,conversion,weka
Platform: UNKNOWN
Classifier: Intended Audience :: Developers
Classifier: Intended Audience :: Information Technology
Classifier: Intended Audience :: Science/Research
Classifier: License :: OSI Approved :: GNU General Public License v3 (GPLv3)
Classifier: Programming Language :: Python :: 2
Classifier: Programming Language :: Python :: 2.7
Classifier: Programming Language :: Python :: 3
Classifier: Programming Language :: Python :: 3.4
Classifier: Programming Language :: Python :: 3.5
Classifier: Topic :: Utilities
